trace_storm/__init__.py
trace_storm/constants.py
trace_storm/logger.py
trace_storm/main.py
trace_storm/request_generator.py
trace_storm/result_analyzer.py
trace_storm/trace_generator.py
trace_storm/trace_player.py
trace_storm/utils.py
tracestorm-0.0.1.dist-info/METADATA
tracestorm-0.0.1.dist-info/WHEEL
tracestorm-0.0.1.dist-info/top_level.txt
tracestorm-0.0.1.dist-info/RECORD
