Metadata-Version: 2.1
Name: tracestorm
Version: 0.0.1
Summary: A replay tool for LLM requests
Author-email: Yao Fu <yao.fu.aisys@gmail.com>
Requires-Dist: openai>=1.58.0
Requires-Dist: vllm>=0.6.3
Requires-Dist: numpy>=1.26.4
Requires-Dist: pandas>=2.2.3
Requires-Dist: seaborn>=0.13.2
Requires-Dist: matplotlib>=3.10
